{
    "projects": [
      {
        "date": "15/5/2024",
        "title": "XCrypto",
        "description": "Built with React, this Bitcoin tracker allows real-time portfolio monitoring, displaying live price updates and market trends seamlessly.",
        "url": "https://react-bitcoin-ochre.vercel.app/",
        "imgSrc": "https://cdn.pixabay.com/photo/2017/12/12/12/44/bitcoin-3014614_960_720.jpg"
      },
  
      {
        "date": "19/12/2024",
        "title": "CountriesData",
        "description": "Built a React app to display real-time country data using APIs, including population, capital, languages, and region details.",
        "url": "https://fluffy-toffee-2c539e.netlify.app/",
        "imgSrc": "https://media.istockphoto.com/id/1329836000/photo/signpost-with-national-flags-of-different-countries.jpg?b=1&s=612x612&w=0&k=20&c=fYp1TC6MPm7Gwu3YzcRxwclp1ludu5_5pBiFNxJ4UYQ="
      },
      {
        "date": "7/12/2023",
        "title": "Sidcup_Golf_House",
        "description": "It's a Frontend Website which has micro animations and scrolling animations. It is desktop based project which uses GSAP features.",
        "url": "https://sidcup-golf-house-theta.vercel.app/",
        "imgSrc": "https://t3.ftcdn.net/jpg/00/08/48/90/360_F_8489083_gyFQj5QhX6ZpoH42Vwasg2ZCl1duhntD.jpg"
      },
  
      {
        "date": "17/10/2023",
        "title": "Weather_WebApp",
        "description": "A React-based weather app providing real-time updates, forecasts, and accurate weather data using APIs for global locations.",
        "url": "https://react-w-sigma.vercel.app/",
        "imgSrc": "https://w0.peakpx.com/wallpaper/262/188/HD-wallpaper-clouds-summer-weather-clouds-weather-summer-nature.jpg"
      },
      {
        "date": "21/12/2024",
        "title": "React_Todo",
        "description": "Built a React-based To-Do app using Axios for API integration, enabling CRUD operations and real-time task management with ease.",
        "url": "https://zingy-pasca-80d7da.netlify.app/",
        "imgSrc": "https://camo.envatousercontent.com/f2df271b1a33ff2cbc67b22af701ed74bd3b72a9/68747470733a2f2f692e706f7374696d672e63632f54326b34674c374a2f4672616d652d31342e6a7067"
      },
     {
        "date": "21/11/2023",
        "title": "Rejouice",
        "description": "It's a Frontend Website which has micro animations and scrolling animations. It is desktop based project which uses GSAP features.",
        "url": "https://effortless-nougat-fb8abc.netlify.app/",
        "imgSrc": "https://i.pinimg.com/736x/b3/e5/d5/b3e5d55c1a3dd3f8950ea8fe5a5c255d.jpg"
      }
    ]
  }
